aioipfs_api/__init__.py
aioipfs_api/autoapi.py
aioipfs_api/client.py
aioipfs_api/exceptions.py
aioipfs_api/http.py
aioipfs_api/tests/__init__.py
aioipfs_api/tests/test_client.py
aioipfs_api/tests/test_linting.py
aioipfs_api-0.1.3.dist-info/LICENSE
aioipfs_api-0.1.3.dist-info/METADATA
aioipfs_api-0.1.3.dist-info/WHEEL
aioipfs_api-0.1.3.dist-info/top_level.txt
aioipfs_api-0.1.3.dist-info/RECORD
