Metadata-Version: 2.1
Name: aioipfs-api
Version: 0.1.3
Summary: Python 3 async client for interacting with the IPFS HTTP API
Home-page: http://github.com/bmuller/aioipfs-api
Author: Brian Muller
Author-email: bamuller@gmail.com
License: MIT
Platform: UNKNOWN
Requires-Dist: aiohttp (>=3.4.0)
Requires-Dist: yarl (>=1.2.6)
